scraping_orbit/__init__.py
scraping_orbit/assets/__init__.py
scraping_orbit/assets/assets_direction.py
scraping_orbit/aws/__init__.py
scraping_orbit/aws/aws_functions.py
scraping_orbit/captcha/__init__.py
scraping_orbit/captcha/captcha_functions.py
scraping_orbit/computer_vision/__init__.py
scraping_orbit/computer_vision/conversions/__init__.py
scraping_orbit/computer_vision/conversions/html.py
scraping_orbit/computer_vision/conversions/pdf.py
scraping_orbit/computer_vision/images/__init__.py
scraping_orbit/computer_vision/images/filters.py
scraping_orbit/computer_vision/images/tables.py
scraping_orbit/computer_vision/images/tesseract_functions.py
scraping_orbit/connection/__init__.py
scraping_orbit/connection/connection_functions.py
scraping_orbit/connection/document_downloaders.py
scraping_orbit/data/__init__.py
scraping_orbit/data/data_merger.py
scraping_orbit/data/dataframe_functions.py
scraping_orbit/data/date_functions.py
scraping_orbit/data/schemas_functions.py
scraping_orbit/mongodb/__init__.py
scraping_orbit/mongodb/mongodb_functions.py
scraping_orbit/multiprocess/__init__.py
scraping_orbit/multiprocess/multiprocess_functions.py
scraping_orbit/parsing/__init__.py
scraping_orbit/parsing/string_parsers.py
scraping_orbit/selenium/__init__.py
scraping_orbit/selenium/selenium_functions.py
scraping_orbit/tracking/__init__.py
scraping_orbit/tracking/performance.py
scraping_orbit/utils/__init__.py
scraping_orbit/utils/code_creation.py
scraping_orbit/utils/doctree_generator.py
scraping_orbit/utils/splitters.py
scraping_orbit-0.0.2.dist-info/LICENSE
scraping_orbit-0.0.2.dist-info/METADATA
scraping_orbit-0.0.2.dist-info/WHEEL
scraping_orbit-0.0.2.dist-info/top_level.txt
scraping_orbit-0.0.2.dist-info/RECORD
